[
  {
    "name": "Dee Nguyen",
    "job_title": "BD Consultant at Hashkey Global | Co-founder at The Real Coin",
    "company": "Hashkey Global and The Real Coin",
    "location": "Vietnam"
  },
  {
    "name": "Çiğdem Gülerman Sauer",
    "job_title": "Neurological Speech Disorders Specialist",
    "company": "Autismedi",
    "location": "Austin, Texas, United States"
  },
  {
    "name": "Marc Valdez",
    "job_title": "Ornamental installer and finisher",
    "company": "A.P. Ornamental",
    "location": "Houston, Texas, United States"
  }
]